IM_GBO_optimizer/GBO.py
IM_GBO_optimizer/__init__.py
IM_GBO_optimizer-2.0.0.dist-info/LICENSE
IM_GBO_optimizer-2.0.0.dist-info/METADATA
IM_GBO_optimizer-2.0.0.dist-info/WHEEL
IM_GBO_optimizer-2.0.0.dist-info/top_level.txt
IM_GBO_optimizer-2.0.0.dist-info/RECORD
