Metadata-Version: 2.1
Name: IM_GBO_optimizer
Version: 2.0.0
Summary: A Mathematical-Based Optimization Method
Author-email: Iman Ahmadianfar <im.ahmadian@gmail.com>
License: MIT License
Project-URL: Homepage, https://www.mathworks.com/matlabcentral/profile/authors/13490648
Project-URL: Bug Tracker, https://github.com/ImanAhm
Classifier: Programming Language :: Python :: 3
Classifier: License :: OSI Approved :: MIT License
Classifier: Operating System :: OS Independent
Requires-Python: >=3.8
License-File: LICENSE
